setup.py
tionsdistribu/Gaussiandistribution.py
tionsdistribu/Generaldistribution.py
tionsdistribu/__init__.py
tionsdistribu.egg-info/PKG-INFO
tionsdistribu.egg-info/SOURCES.txt
tionsdistribu.egg-info/dependency_links.txt
tionsdistribu.egg-info/not-zip-safe
tionsdistribu.egg-info/top_level.txt