Metadata-Version: 1.0
Name: tionsdistribu
Version: 1.0
Summary: Code for distributions
Home-page: UNKNOWN
Author: UNKNOWN
Author-email: UNKNOWN
License: UNKNOWN
Platform: UNKNOWN
